gfanno/Filter.py
gfanno/GeneFamilyAnno.py
gfanno/__init__.py
gfanno/__main__.py
gfanno/dataset/hmm/2OG-FeII_Oxy.hmm
gfanno/dataset/hmm/AMP-binding.hmm
gfanno/dataset/hmm/AMP-binding_C.hmm
gfanno/dataset/hmm/Chal_sti_synt_C.hmm
gfanno/dataset/hmm/Chal_sti_synt_N.hmm
gfanno/dataset/hmm/Chalcone.hmm
gfanno/dataset/hmm/DIOX_N.hmm
gfanno/dataset/hmm/Epimerase.hmm
gfanno/dataset/hmm/Lyase_aromatic.hmm
gfanno/dataset/hmm/NmrA.hmm
gfanno/dataset/hmm/PPO1_DWL.hmm
gfanno/dataset/hmm/PPO1_KFDV.hmm
gfanno/dataset/hmm/Peptidase_S10.hmm
gfanno/dataset/hmm/UGTnew.hmm
gfanno/dataset/hmm/p450.hmm
gfanno/dataset/seed/4CL.seed.fasta
gfanno/dataset/seed/ANR.seed.fasta
gfanno/dataset/seed/ANS.seed.fasta
gfanno/dataset/seed/C4H.seed.fasta
gfanno/dataset/seed/CHI.seed.fasta
gfanno/dataset/seed/CHS.seed.fasta
gfanno/dataset/seed/DFR.seed.fasta
gfanno/dataset/seed/F33H.seed.fasta
gfanno/dataset/seed/F35H.seed.fasta
gfanno/dataset/seed/F3H.seed.fasta
gfanno/dataset/seed/FLS.seed.fasta
gfanno/dataset/seed/FNSII.seed.fasta
gfanno/dataset/seed/LAR.seed.fasta
gfanno/dataset/seed/LDOX.seed.fasta
gfanno/dataset/seed/PAL.seed.fasta
gfanno/dataset/seed/PPO.seed.fasta
gfanno/dataset/seed/SCPL4.seed.fasta
gfanno/dataset/seed/SCPL5.seed.fasta
gfanno/dataset/seed/UGT84A.seed.fasta
gfanno/utils/__init__.py
gfanno/utils/commander.py
gfanno/utils/config.py
gfanno/utils/fasta.py
gfanno/utils/filter_old.py
gfanno/utils/log.py
gfanno-1.4.dist-info/LICENSE
gfanno-1.4.dist-info/METADATA
gfanno-1.4.dist-info/WHEEL
gfanno-1.4.dist-info/entry_points.txt
gfanno-1.4.dist-info/top_level.txt
gfanno-1.4.dist-info/RECORD
