Metadata-Version: 2.1
Name: gfanno
Version: 1.4
Summary: Gene Family Annotation
Home-page: https://github.com/qunjie-zhang/gfanno
Author: ['wangzt', 'duliuxu']
Author-email: interestingcn01@gmail.com
Keywords: gene family,bioinformatics,pipline
Classifier: Development Status :: 5 - Production/Stable
Classifier: License :: OSI Approved :: Apache Software License
Classifier: Operating System :: OS Independent
Classifier: Programming Language :: Python :: 3.5
Classifier: Programming Language :: Python :: 3.6
Classifier: Programming Language :: Python :: 3.7
Classifier: Programming Language :: Python :: 3.8
Classifier: Programming Language :: Python :: 3.9
Classifier: Programming Language :: Python :: 3.10
Classifier: Programming Language :: Python :: 3.11
Requires-Python: >=3.5
License-File: LICENSE
